limedev/__init__.py
limedev/__main__.py
limedev/_api.py
limedev/_aux.py
limedev/_cli.py
limedev/benchmarking.py
limedev/cli.py
limedev/linting.py
limedev/profiling.py
limedev/py.typed
limedev/readme.py
limedev/typing.py
limedev/unittesting.py
limedev/configs/3.10/pyrefly.toml
limedev/configs/3.10/ruff.toml
limedev/configs/3.11/pyrefly.toml
limedev/configs/3.11/ruff.toml
limedev/configs/3.12/pyrefly.toml
limedev/configs/3.12/ruff.toml
limedev/configs/3.13/pyrefly.toml
limedev/configs/3.13/ruff.toml
limedev/configs/3.14/pyrefly.toml
limedev/configs/3.14/ty.toml
limedev/configs/fallback/mypy.ini
limedev/configs/fallback/pyrefly.toml
limedev/configs/fallback/pytest.ini
limedev/configs/fallback/ruff.toml
limedev/configs/fallback/ty.toml
limedev/package/__init__.py
limedev/package/__main__.py
limedev/package/_api.py
limedev/package/_cli.py
limedev/test/_api.py
limedev-0.7.2.dist-info/licenses/LICENSE.txt
limedev-0.7.2.dist-info/METADATA
limedev-0.7.2.dist-info/WHEEL
limedev-0.7.2.dist-info/entry_points.txt
limedev-0.7.2.dist-info/top_level.txt
limedev-0.7.2.dist-info/RECORD
