Metadata-Version: 2.4
Name: limedev
Version: 0.7.2
Summary: Toolkit for Python development, especially packaging 
Author: Limespy
License-Expression: MIT
Project-URL: Homepage, https://github.com/limespy/limedev
Project-URL: Changelog, https://github.com/limespy/limedev/blob/main/README.md#Changelog
Project-URL: Issue Tracker, https://github.com/limespy/limedev/issues
Classifier: Development Status :: 3 - Alpha
Classifier: Operating System :: Microsoft :: Windows
Classifier: Operating System :: POSIX
Classifier: Programming Language :: Python :: 3
Classifier: Programming Language :: Python :: 3 :: Only
Classifier: Programming Language :: Python :: 3.11
Classifier: Programming Language :: Python :: 3.12
Classifier: Programming Language :: Python :: 3.13
Classifier: Programming Language :: Python :: 3.14
Requires-Python: >=3.11
License-File: LICENSE.txt
Provides-Extra: all
Requires-Dist: limedev[benchmarking]; extra == "all"
Requires-Dist: limedev[linting]; extra == "all"
Requires-Dist: limedev[package]; extra == "all"
Requires-Dist: limedev[profiling]; extra == "all"
Requires-Dist: limedev[readme]; extra == "all"
Requires-Dist: limedev[test]; extra == "all"
Requires-Dist: limedev[typing]; extra == "all"
Requires-Dist: limedev[unittesting]; extra == "all"
Requires-Dist: limedev[unittests]; extra == "all"
Provides-Extra: benchmarking
Requires-Dist: pywin32>=308; (sys_platform == "win32" and python_version <= "3.13") and extra == "benchmarking"
Requires-Dist: pyyaml>=6.0; extra == "benchmarking"
Provides-Extra: linting
Requires-Dist: ruff>=0.9.1; extra == "linting"
Provides-Extra: package
Requires-Dist: build>=0.10.0; extra == "package"
Requires-Dist: tomli-w>=1.0.0; extra == "package"
Requires-Dist: wheel>=0.38; extra == "package"
Provides-Extra: profiling
Requires-Dist: gprof2dot>=2022.7.29; extra == "profiling"
Provides-Extra: readme
Requires-Dist: yamdog>=0.6.0; extra == "readme"
Provides-Extra: typing
Requires-Dist: limedev[typing-mypy]; extra == "typing"
Requires-Dist: limedev[typing-pyrefly]; extra == "typing"
Requires-Dist: limedev[typing-ty]; extra == "typing"
Provides-Extra: typing-mypy
Requires-Dist: mypy>=1.14.0; extra == "typing-mypy"
Provides-Extra: typing-pyrefly
Requires-Dist: pyrefly>=0.21.0; extra == "typing-pyrefly"
Provides-Extra: typing-ty
Requires-Dist: ty>=0.0.1a11; extra == "typing-ty"
Provides-Extra: unittesting
Requires-Dist: pytest>=7.2.0; extra == "unittesting"
Requires-Dist: pytest-cov>=4.0.0; extra == "unittesting"
Dynamic: license-file
